sayo.py
sayo-0.1.dev0.data/scripts/sayo.py
sayo-0.1.dev0.dist-info/DESCRIPTION.rst
sayo-0.1.dev0.dist-info/METADATA
sayo-0.1.dev0.dist-info/RECORD
sayo-0.1.dev0.dist-info/WHEEL
sayo-0.1.dev0.dist-info/metadata.json
sayo-0.1.dev0.dist-info/top_level.txt
