Metadata-Version: 2.0
Name: sayo
Version: 0.1.dev0
Summary: An incomplete socket.io client written using asyncio.
Home-page: https://github.com/scharron/sayo/
Author: Samuel Charron
Author-email: samuel.charron@gmail.com
License: MIT
Platform: any
Classifier: Development Status :: 3 - Alpha
Classifier: Intended Audience :: Developers
Classifier: License :: OSI Approved :: MIT License
Classifier: Framework :: AsyncIO
Classifier: Topic :: System :: Networking
Classifier: Topic :: Software Development :: Libraries :: Application Frameworks
Classifier: Programming Language :: Python :: 3.6
